dsdb/__init__.py
dsdb/_utils_dsdb.py
dsdb-0.2.0.dist-info/LICENSE
dsdb-0.2.0.dist-info/METADATA
dsdb-0.2.0.dist-info/WHEEL
dsdb-0.2.0.dist-info/top_level.txt
dsdb-0.2.0.dist-info/RECORD
