Metadata-Version: 2.1
Name: dsdb
Version: 0.2.0
Summary: One-line database manager for Data Science workloads.
Home-page: https://github.com/buildnn/dsdb
Author: Giacomo Barone, Buildnn
Author-email: giacomo.barone@buildnn.com
License: The MIT License (MIT)
Requires-Dist: attrs
Provides-Extra: all
Requires-Dist: boto3 ; extra == 'all'
Requires-Dist: pymongo ; extra == 'all'
Requires-Dist: redis ; extra == 'all'
Requires-Dist: sqlalchemy ; extra == 'all'
Requires-Dist: psycopg2-binary ; extra == 'all'
Provides-Extra: dev
Requires-Dist: boto3 ; extra == 'dev'
Requires-Dist: pymongo ; extra == 'dev'
Requires-Dist: redis ; extra == 'dev'
Requires-Dist: sqlalchemy ; extra == 'dev'
Requires-Dist: psycopg2-binary ; extra == 'dev'
Requires-Dist: pytest ; extra == 'dev'
Requires-Dist: pytest-cov ; extra == 'dev'
Requires-Dist: black ; extra == 'dev'
Requires-Dist: flake8 ; extra == 'dev'
Provides-Extra: dynamodb
Requires-Dist: boto3 ; extra == 'dynamodb'
Provides-Extra: mongo
Requires-Dist: pymongo ; extra == 'mongo'
Provides-Extra: nosql
Requires-Dist: boto3 ; extra == 'nosql'
Requires-Dist: pymongo ; extra == 'nosql'
Requires-Dist: redis ; extra == 'nosql'
Provides-Extra: postgres
Requires-Dist: sqlalchemy ; extra == 'postgres'
Requires-Dist: psycopg2-binary ; extra == 'postgres'
Provides-Extra: redis
Requires-Dist: redis ; extra == 'redis'
